pyfml/__init__.py
pyfml/factory.py
pyfml/internal/__init__.py
pyfml/internal/callables.py
pyfml/internal/conf.py
pyfml/internal/dag.py
pyfml/internal/typedefs.py
pyfml-0.1.11.dist-info/LICENSE
pyfml-0.1.11.dist-info/WHEEL
pyfml-0.1.11.dist-info/METADATA
pyfml-0.1.11.dist-info/RECORD
