Metadata-Version: 2.1
Name: pyfml
Version: 0.1.11
Summary: python factory meta language
Author: Ben G
Author-email: ben.gordon@toasttab.com
Requires-Python: >=3.6,<4.0
Classifier: Programming Language :: Python :: 3
Classifier: Programming Language :: Python :: 3.6
Classifier: Programming Language :: Python :: 3.7
Requires-Dist: purl (>=1.5,<2.0)
Requires-Dist: toml (>=0.10.0,<0.11.0)
